LICENSE.txt
MANIFEST.in
README.md
VERSION
setup.cfg
setup.py
atsky/__init__.py
atsky.egg-info/PKG-INFO
atsky.egg-info/SOURCES.txt
atsky.egg-info/dependency_links.txt
atsky.egg-info/top_level.txt
atsky/utils/__init__.py
atsky/utils/_inner/__init__.py
atsky/utils/_inner/strutils.py