Metadata-Version: 2.1
Name: atsky
Version: 0.0.1
Summary: atsky
Home-page: https://gitee.com/chaos-god/atsky.git
Author: atsky
Author-email: 9239867+chaos-god@user.noreply.gitee.com
License: UNKNOWN
Platform: UNKNOWN
License-File: LICENSE.txt
